control_unit/control_unit.v
module control_unit (input[31:0] inst, output reg b_beq, b_jal, b_jalr, reg_write, mem_to_reg, mem_write,
                output reg[3:0] alu_control, output reg alu_src, output reg[2:0] imm_control);
    
    // *****  IMM Control codes ***** //    // *****  ALU Control codes ***** //
    //            R -> 000            //    //            + -> 0000           //
    //            I -> 001            //    //            & -> 0001           //
    //            S -> 010            //    //            - -> 0010           //
    //            B -> 011            //    //            < -> 0011           //
    //            U -> 100            //    //            / -> 0100           //
    //            J -> 101            //    //            % -> 0101           //
    // ****************************** //    //           << -> 0110           //
                                            //           >> -> 0111           //
                                            //          >>> -> 1000           //
                                            // ****************************** //

    always @(inst) begin
        case(inst[6:0])
            7'b0110011: begin // R-type operations
                imm_control <= 3'b000;
                reg_write <= 1;
                imm_control <= 0;
                alu_src <= 0;
                mem_to_reg <= 0;
                mem_write <= 0;
                b_beq <= 0;
                b_jal <= 0;
                b_jalr <= 0;

                //add
                if (inst[31:25] == 7'b0 && inst[14:12] == 3'b0) 
                    alu_control <= 4'b0;

                //and
                if (inst[31:25] == 7'b0 && inst[14:12] == 3'b111) 
                    alu_control <= 4'b0001;

                //sub
                if (inst[31:25] == 7'b0100000 && inst[14:12] == 3'b0) 
                    alu_control <= 4'b0010;
                
                //slt
                if (inst[31:25] == 7'b0 && inst[14:12] == 3'b010) 
                    alu_control <= 4'b0011;

                //div
                if (inst[31:25] == 7'b0000001 && inst[14:12] == 3'b100) 
                    alu_control <= 4'b0100;

                //rem
                if (inst[31:25] == 7'b0000001 && inst[14:12] == 3'b110) 
                    alu_control <= 4'b0101;

                //sll
                if (inst[31:25] == 7'b0 && inst[14:12] == 3'b001) 
                    alu_control <= 4'b0110;
                
                //srl
                if (inst[31:25] == 7'b0 && inst[14:12] == 3'b101) 
                    alu_control <= 4'b0111;

                //sra
                if (inst[31:25] == 7'b0100000 && inst[14:12] == 3'b101) 
                    alu_control <= 4'b1000; 
            end
            
            //addi
            7'b0010011: begin
                imm_control <= 3'b001;
                reg_write <= 1;
                imm_control <= 1;
                alu_src <= 1;
                mem_to_reg <= 0;
                mem_write <= 0;
                b_beq <= 0;
                b_jal <= 0;
                b_jalr <= 0;
                alu_control <= 4'b0;
            end

            //lw
            7'b0000011: begin
                imm_control <= 3'b001;
                reg_write <= 1;
                imm_control <= 1;
                alu_src <= 1;
                mem_to_reg <= 1;
                mem_write <= 0;
                b_beq <= 0;
                b_jal <= 0;
                b_jalr <= 0;
                alu_control <= 4'b0;
            end

            //jalr
            7'b1100111: begin
                imm_control <= 3'b001;
                reg_write <= 1;
                imm_control <= 1;
                alu_src <= 1;
                mem_to_reg <= 0;
                mem_write <= 0;
                b_beq <= 0;
                b_jal <= 0;
                b_jalr <= 1;
                alu_control <= 4'b0;
            end

        endcase
    end
endmodule

control_unit/control_unit_tb.v
module control_unit_tb();

    reg[31:0] inst;
    wire b_beq, b_jal, b_jalr, reg_write, mem_to_reg, mem_write;
    wire[3:0] alu_control; 
    wire alu_src;
    wire[2:0] imm_control;

    control_unit test(inst, b_beq, b_jal, b_jalr, reg_write, mem_to_reg, mem_write, alu_control, alu_src, imm_control);
    
    initial begin
        $dumpfile("test");
        $dumpvars;

        inst <= 32'b00000000000000000000000000110011;
        #10

        inst <= 32'b00000000000000000111000000110011;
        #10

        inst <= 32'b01000000000000000000000000110011;
        #10

        inst <= 32'b00000000000000000010000000110011;
        #10
        //5
        inst <= 32'b00000010000000000100000000110011;
        #10

        inst <= 32'b00000010000000000110000000110011;
        #10

        inst <= 32'b00000000000000000001000000110011;
        #10

        inst <= 32'b00000000000000000101000000110011;
        #10

        inst <= 32'b01000000000000000101000000110011;
        #10

        $finish;
    end

endmodule

control_unit/test.vcd
$date
	Thu Oct 27 03:10:35 2022
$end
$version
	Icarus Verilog
$end
$timescale
	1s
$end
$scope module control_unit_tb $end
$var wire 1 ! reg_write $end
$var wire 1 " mem_write $end
$var wire 1 # mem_to_reg $end
$var wire 3 $ imm_control [2:0] $end
$var wire 1 % b_jalr $end
$var wire 1 & b_jal $end
$var wire 1 ' b_beq $end
$var wire 1 ( alu_src $end
$var wire 4 ) alu_control [3:0] $end
$var reg 32 * inst [31:0] $end
$scope module test $end
$var wire 32 + inst [31:0] $end
$var reg 4 , alu_control [3:0] $end
$var reg 1 ( alu_src $end
$var reg 1 ' b_beq $end
$var reg 1 & b_jal $end
$var reg 1 % b_jalr $end
$var reg 3 - imm_control [2:0] $end
$var reg 1 # mem_to_reg $end
$var reg 1 " mem_write $end
$var reg 1 ! reg_write $end
$upscope $end
$upscope $end
$enddefinitions $end
#0
$dumpvars
b0 -
b0 ,
b110011 +
b110011 *
b0 )
0(
0'
0&
0%
b0 $
0#
0"
1!
$end
#10
b1 )
b1 ,
b111000000110011 *
b111000000110011 +
#20
b10 )
b10 ,
b1000000000000000000000000110011 *
b1000000000000000000000000110011 +
#30
b11 )
b11 ,
b10000000110011 *
b10000000110011 +
#40
b100 )
b100 ,
b10000000000100000000110011 *
b10000000000100000000110011 +
#50
b101 )
b101 ,
b10000000000110000000110011 *
b10000000000110000000110011 +
#60
b110 )
b110 ,
b1000000110011 *
b1000000110011 +
#70
b111 )
b111 ,
b101000000110011 *
b101000000110011 +
#80
b1000 )
b1000 ,
b1000000000000000101000000110011 *
b1000000000000000101000000110011 +
#90
b0 )
b0 ,
1(
b1 $
b1 -
b10011 *
b10011 +
